<?xml version="1.0" encoding="UTF-8"?>

<strings>
	<entity>Entidade</entity>
	
	<entityType>
		<type id="groups">Grupos</type>
		<type id="categories">Categorias</type>
		<type id="operations">Operações</type>
		<type id="regions">Regiões</type>
	</entityType>
	
	<srcLang>Língua de origem</srcLang>
	<desLang>Língua de destino</desLang>
	
			<!-- Buttons -->
	
	<save>Gravar</save>
	<refresh>Refrescar</refresh>
	
	<!-- validator messages -->
	
	<validator>
		<length>
			<cannotBeEmpty>O texto de localizção não deve ficar vazio.</cannotBeEmpty>
			<invalidMaxSize>O texto de localizção deve conter {VALUE} carácteres no máximo.</invalidMaxSize>
		</length>		
	</validator>
	
	<!-- display messages -->
	
	<cannotGetList>Não consegue carregar a lista de entidades</cannotGetList>
	<cannotSave>Um erro ocorreu durante da gravação</cannotSave>
	
	<!-- tooltips -->
	
	<tips>
	</tips>
	
</strings>

