<!--
  ~ Copyright (C) 2001-2016 Food and Agriculture Organization of the
  ~ United Nations (FAO-UN), United Nations World Food Programme (WFP)
  ~ and United Nations Environment Programme (UNEP)
  ~
  ~ This program is free software; you can redistribute it and/or modify
  ~ it under the terms of the GNU General Public License as published by
  ~ the Free Software Foundation; either version 2 of the License, or (at
  ~ your option) any later version.
  ~
  ~ This program is distributed in the hope that it will be useful, but
  ~ WITHOUT ANY WARRANTY; without even the implied warranty of
  ~ MERCHANTABILITY or FITNESS FOR A PARTICULAR PURPOSE. See the GNU
  ~ General Public License for more details.
  ~
  ~ You should have received a copy of the GNU General Public License
  ~ along with this program; if not, write to the Free Software
  ~ Foundation, Inc., 51 Franklin St, Fifth Floor, Boston, MA 02110-1301, USA
  ~
  ~ Contact: Jeroen Ticheler - FAO - Viale delle Terme di Caracalla 2,
  ~ Rome - Italy. email: geonetwork@osgeo.org
  -->

<!-- The properties 'jar', 'outfile', 'fileVersion', 'txtFileVersion',
     'productVersion' and 'txtProductVersion' are overruled by the
     installer build.xml file -->

<launch4jConfig>
  <dontWrapJar>false</dontWrapJar>
  <headerType>0</headerType>
  <jar>../geonetwork-2.6.0/geonetwork-install.jar</jar>
  <outfile>../geonetwork-2.6.0/geonetwork-install.exe</outfile>
  <errTitle>GeoNetwork opensource Installation Error</errTitle>
  <jarArgs></jarArgs>
  <chdir></chdir>
  <customProcName>false</customProcName>
  <stayAlive>false</stayAlive>
  <icon>../installer.ico</icon>
  <jre>
    <!--    <path>jre1.5.0_12</path> -->
    <minVersion>1.5.0</minVersion>
    <!--    <maxVersion>1.5.0_15</maxVersion> -->
    <initialHeapSize>256</initialHeapSize>
    <maxHeapSize>512</maxHeapSize>
    <args></args>
  </jre>
  <splash>
    <file>../splash.bmp</file>
    <waitForWindow>true</waitForWindow>
    <timeout>60</timeout>
    <timeoutErr>true</timeoutErr>
  </splash>
  <versionInfo>
    <fileVersion>2.6.0.0</fileVersion>
    <txtFileVersion>2.6.0 0</txtFileVersion>
    <fileDescription>GeoNetwork opensource Windows Installer</fileDescription>
    <copyright>OSGeo (http://www.osgeo.org)</copyright>
    <productVersion>2.6.0.0</productVersion>
    <txtProductVersion>2.6.0 0</txtProductVersion>
    <productName>GeoNetwork opensource</productName>
    <companyName></companyName>
    <internalName>geonetwork-install.jar</internalName>
    <originalFilename>geonetwork-install.exe</originalFilename>
  </versionInfo>
</launch4jConfig>
